jobrex/__init__.py
jobrex/client.py
jobrex/models.py
jobrex/utils.py
jobrex/tests/README.md
jobrex/tests/__init__.py
jobrex/tests/conftest.py
jobrex/tests/test_client.py
jobrex/tests/test_imports.py
jobrex/tests/test_integration.py
jobrex/tests/test_models.py
jobrex/tests/test_utils.py
jobrex_client-0.1.0a6.dist-info/METADATA
jobrex_client-0.1.0a6.dist-info/WHEEL
jobrex_client-0.1.0a6.dist-info/licenses/LICENSE
jobrex_client-0.1.0a6.dist-info/RECORD
