Metadata-Version: 2.4
Name: jobrex-client
Version: 0.1.0a6
Summary: Python client for the Jobrex API
Project-URL: Homepage, https://github.com/jobrex-ai/jobrex-client
Project-URL: Bug Tracker, https://github.com/jobrex-ai/jobrex-client/issues
Author-email: Jobrex Team <support@jobrex.ai>
License: MIT
License-File: LICENSE
Classifier: Development Status :: 3 - Alpha
Classifier: Intended Audience :: Developers
Classifier: License :: OSI Approved :: MIT License
Classifier: Programming Language :: Python :: 3
Classifier: Programming Language :: Python :: 3.8
Classifier: Programming Language :: Python :: 3.9
Classifier: Programming Language :: Python :: 3.10
Classifier: Programming Language :: Python :: 3.11
Requires-Python: >=3.8
Requires-Dist: requests>=2.25.0
Provides-Extra: dev
Requires-Dist: pytest-cov>=4.0.0; extra == 'dev'
Requires-Dist: pytest>=7.0.0; extra == 'dev'
